FlowPilot/__init__.py
FlowPilot/flowpilot.py
flowpilot-0.1.1.dist-info/LICENSE
flowpilot-0.1.1.dist-info/METADATA
flowpilot-0.1.1.dist-info/WHEEL
flowpilot-0.1.1.dist-info/top_level.txt
flowpilot-0.1.1.dist-info/RECORD
